{"domain": "med_Anatomy_00", "source": "medmcqa", "facts": [{"context": "Which of the following are not a branch of external carotid Aery in Kiesselbach's plexus.", "truth": "Anterior ethmoidal aery", "distractors": ["Sphenopalatine aery", "Greater palatine aery", "Septal branch of superior labial aery"]}, {"context": "Which of the following is the only complete cailage ring in the respiratory tree?", "truth": "Cricoid cailage", "distractors": ["Thyroid cailage", "Cunieform cailage", "Epiglottis"]}, {"context": "Which pa of brachial plexus do not give branches", "truth": "Division", "distractors": ["Root", "Cord", "Trunk"]}, {"context": "The cells which will proliferate from top to bottom of villi are:", "truth": "Paneth cells", "distractors": ["Chief cells", "Goblet cells", "Parietal cells"]}, {"context": "Retraction of mandible is achieved by:", "truth": "Temporalis", "distractors": ["Lateral pterygoid", "Medial pterygoid", "Masseter"]}, {"context": "Waldeyer's lymphatic chain is formed by all except", "truth": "Post auricular nodes", "distractors": ["Palatine tonsils", "Pharyngeal tonsils", "Tubal and lingual tonsils"]}, {"context": "Artery palpable at the anterior border of the masseter is :", "truth": "Facial artery", "distractors": ["Superficial temporal artery", "Lingual artery", "Maxillary artery"]}, {"context": "Visual cortex is present in the:", "truth": "Occipital lobe", "distractors": ["Temporal lobe", "Frontal lobe", "Parietal lobe"]}, {"context": "Tonsils developed from:", "truth": "Ventral part of 2nd pouch.", "distractors": ["Ventral part of 3rd pouch.", "Dorsal part of 2nd pouch.", "Ventral part of 3rd pouch."]}, {"context": "Motor supply of infrahyoid muscle is:", "truth": "Branches of cervical plexus", "distractors": ["Vagus nerve", "Glossopharyngeal nerve", "Mandibular nerve"]}, {"context": "Which of the following structure is not present on floor of third ventricle?", "truth": "Third nerve", "distractors": ["Optic stalk", "Infundibulum", "Mammillary body"]}, {"context": "Reticular fibers of collagen tissues are present in all of the following except:", "truth": "Thymus", "distractors": ["Spleen", "Bone marrow", "Lymph node"]}, {"context": "Which is a direct content of cavernous sinus?", "truth": "Abducent nerve", "distractors": ["Ophthalmic division of trigeminal nerve", "Trochlear nerve", "Oculomotor nerve"]}, {"context": "Pre-maxillary hard palate is supplied by which nerve", "truth": "Nasopalatine nerve", "distractors": ["Pharyngeal branch of glossopharyngeal nerve", "Greater palatine nerve", "Tensor palatine nerve"]}, {"context": "All the following muscles of larynx are supplied by the recurrent laryngeal nerve except:", "truth": "Cricothyroid", "distractors": ["Cricohyoid", "Arytenoid", "Aryepiglotticus"]}, {"context": "All of the following are developed from Meckel's cartilage except:", "truth": "Stapes", "distractors": ["Zygomatic bone", "Malleus", "Incus"]}, {"context": "The fifth nerve innervates the following:", "truth": "Mylohyoid, anterior belly of digastric, and tensor tympani", "distractors": ["Mylohyoid, anterior and posterior belly of digastric", "Mylohyoid, posterior belly of digastric and tensor tympani", "Mylohyoid, posterior belly of digastric, Stapedius and tensor tympani"]}, {"context": "The frontal paranasal sinus drains into the:", "truth": "Middle meatus", "distractors": ["Superior meatus", "Inferior meatus", "Spheno-ethmoidal recess"]}, {"context": "Skin of the entire upper lip is supplied by:", "truth": "Maxillary nerve.", "distractors": ["Facial nerve.", "Mandibular nerve.", "None."]}, {"context": "Which marker shows holocrine gland?", "truth": "A", "distractors": ["B", "C", "D"]}, {"context": "Mandibular process of each side fuse to form:", "truth": "Both.", "distractors": ["Lower lip.", "Lower jaw.", "None."]}, {"context": "The special visceral afferent fibres of the facial nerve are located in which nuclei:", "truth": "Nucleus of tractus solitarius", "distractors": ["Motor nucleus", "Nucleus ambiguous", "Lacrimatory nucleus"]}, {"context": "Action of the muscle marked (with arrow) on mandible is", "truth": "Elevation", "distractors": ["Depression", "Retraction", "Protraction"]}, {"context": "Which of the following is innervated by the vagus nerve?", "truth": "The levator veli palatine (levator palatini)", "distractors": ["The posterior belly of digastric", "Mylohyoid", "The tensor veli palatine (tensor palatini)"]}, {"context": "Among all of the following foramens in the base of skull, which is, the most posteriorly present:", "truth": "Foramen spinosum", "distractors": ["Foramen rotundum", "Foramen ovale", "All at same level"]}, {"context": "Nucleus in brain common to IX, X and XI cranial nerves:", "truth": "Nucleus ambiguus", "distractors": ["Nucleus solitarius", "Dentate nucleus", "Red nucleus"]}, {"context": "Lymph from tongue not drained by following vessels", "truth": "Ventral", "distractors": ["Central", "Posterior", "Marginal"]}, {"context": "The part of the mandible which ossify in cartilage is:", "truth": "All of the above", "distractors": ["Coronoid process", "Condylar process", "Upper half of ramus above the level of mandibular foramen"]}, {"context": "Upper lip is formed by the fusion of:", "truth": "Maxillary, lateral nasal, median nasal process.", "distractors": ["Maxillary and lateral nasal process.", "Lateral nasal and median nasal process.", "Maxillary, mandibular, lateral nasal, median nasal process."]}, {"context": "Which of the following muscles causes the forward movement of the condyle in the glenoid fossa?", "truth": "Lateral pterygoid", "distractors": ["Masseter", "Temporalis", "Medial pterygoid"]}, {"context": "Which of the following muscle divides the sub-mandibular gland into a superficial and deep part?", "truth": "Mylohyoid", "distractors": ["Genioglossus", "Sternohyoid", "Digastric"]}, {"context": "All are structures lying deep to the hyoglossus muscle except:", "truth": "Hypoglossal nerve", "distractors": ["Lingual artery", "Stylohyoid muscle", "Geniohyoid muscle"]}, {"context": "Injury to the right mandibular nerve as it passes through foramen ovale produces the following effects:", "truth": "Loss of general sensation to anterior 2/3 of tongue", "distractors": ["Loss of taste from the anterior 2/3 of tongue", "Deviation of the tongue to the left", "Deviation of chin to left when mouth is opened"]}, {"context": "When a patient is asked to say 'ah' , if the uvula is drawn upwards to the left, the cranial nerve likely to be damaged is", "truth": "Rt accessory", "distractors": ["Vagus", "Lt accessory", "Hypoglossal"]}, {"context": "Inferior alveolar nerve runs:", "truth": "Lateral to medial pterygoid", "distractors": ["Medial to lateral pterygoid", "From Infratemporal fossa", "Lateral to lateral pterygoid"]}, {"context": "All of the following bones are involves in wrist joint formation EXCEPT?", "truth": "Ulna", "distractors": ["Scaphoid", "Radius", "Triquetral"]}, {"context": "Anterior division of mandibular nerve has:", "truth": "One sensory and all motor branches", "distractors": ["One motor and all sensory branches", "All motor branches", "All sensory branches"]}, {"context": "The lateral lingual swellings and tuberculum impar give rise to:", "truth": "Anterior 2/3 of tongue", "distractors": ["Anterior 1/3 of tongue", "Posterior 1/3 of tongue", "Posterior 2/3 of tongue"]}, {"context": "Anterior limit of infratemporal fossa is:", "truth": "Maxillary posterior wall", "distractors": ["Lateral pterygoid plate", "Pterygomaxillary fissure", "Mastoid process"]}, {"context": "Golgi tendon organs used to detect ?", "truth": "Tension of muscle", "distractors": ["Dynamic", "Static", "All"]}, {"context": "Root value of cremaster reflex is", "truth": "L1, L2", "distractors": ["L2, L3", "S1, S2", "S3, S4"]}, {"context": "All of the following are true about venous drainage of esophagus except:", "truth": "The cervical esophagus drains directly into the right brachiocephalic vein", "distractors": ["Thoracic esophagus drains into the azygos vein", "Esophageal veins drain into a submucosal plexus", "Lower esophageal veins anastomose with the left gastric vein"]}, {"context": "The 3 embryonic germ layers: ectoderm, mesoderm and endoderm are derived from:", "truth": "Epiblast only", "distractors": ["Ectoderm from epiblast; mesoderm and endoderm from hypoblast", "Ectoderm and mesoderm from epiblast; endoderm from hypoblast", "Hypoblast only"]}, {"context": "Reichert's cartilage is:", "truth": "2nd arch cartilage.", "distractors": ["1st arch cartilage.", "3rd arch cartilage.", "4th arch cartilage."]}, {"context": "On applying pressure on angle of jaw while maintaining patent airway which nerve is likely to be damaged:", "truth": "7th", "distractors": ["6th", "4th", "9th"]}, {"context": "Which of the following is developed from the 1st arch:", "truth": "Spenomandibular ligament.", "distractors": ["Stylohyoid ligament.", "Stapes.", "Styloid process."]}, {"context": "True about occulomotor nerve are all except", "truth": "Passes through inferior orbital fissure", "distractors": ["Carries parasympathetic fibres", "Causes constriction of pupils", "Supplies inferior oblique muscle"]}, {"context": "Retraction of the protruded mandible is done by", "truth": "Temporalis", "distractors": ["Medial Pterygoid", "Lateral pterygoid", "Masseter"]}, {"context": "Type of skull seen in Beckwith hypoglycemic syndrome and fanconi syndrome:", "truth": "Microcephaly.", "distractors": ["Platycephaly.", "Anencephaly.", "Brachcephaly."]}, {"context": "True statements about osteoblasts are all except:", "truth": "Have a plasma membrane showing multiple folds", "distractors": ["Derived from osteoprogenitor cells", "Regulated by BM P", "Have neuropeptide receptors"]}, {"context": "Inferiohyroid aery is a branch ol?", "truth": "Thyrocervical trunk", "distractors": ["ICA", "Costocervical trunk", "ECA"]}, {"context": "All are sensory to the palate except:", "truth": "Hypoglossal nerve", "distractors": ["Maxillary division of the trigeminal nerve", "Facial nerve", "Glossopharyngeal nerve"]}, {"context": "What is the nerve supply of the angle of the jaw?", "truth": "Greater auricular nerve", "distractors": ["Mandibular nerve", "Maxillary nerve", "Lesser occipital nerve"]}, {"context": "What is the location of Meissner's corpuscles?", "truth": "Papillary dermis", "distractors": ["Lucidum", "Basale", "Reticular dermis"]}, {"context": "All of the following are structures in the lateral wall of cavernous sinus except:", "truth": "Optic chiasma", "distractors": ["Occulomotor nerve", "Ophthalmic nerve", "Maxillary nerve"]}, {"context": "Compament of leg without neurovascular bundle?", "truth": "Superficial posterior", "distractors": ["Anterior", "Lateral", "Deep posterior"]}, {"context": "Brachcephaly with narrow foramen magnum is seen in:", "truth": "Achondroplasia.", "distractors": ["Down syndrome.", "Fanconi syndrome.", "Cleidocranial dysplasia."]}, {"context": "Which of the following finger has two dorsal interossei (AIIMS May 2019)", "truth": "Middle", "distractors": ["Little", "Ring", "Index"]}, {"context": "Facial nerve innervates all of the following except:", "truth": "Anterior belly of digastric", "distractors": ["Platysma", "Stapedius", "Auricular muscles"]}, {"context": "Spinal cord ends at what level in adults?", "truth": "L1", "distractors": ["T12", "L2", "L3"]}, {"context": "Arterial supply of Submandibular gland is through which branch of ECA:", "truth": "Facial", "distractors": ["Ascending pharyngeal", "Superior pharyngeal", "Maxillary"]}, {"context": "All of the following bones are involves in wrist joint formation; except:", "truth": "Ulna", "distractors": ["Scaphoid", "Radius", "Triquetral"]}, {"context": "Mesodermal basis of lateral part of lip is formed by:", "truth": "Maxillary process.", "distractors": ["Frontonasal process.", "Globular process.", "All of the above"]}, {"context": "Sensory supply of cornea is by?", "truth": "Nasolacrimal nerve (probably printing mistake - probably Nasociliary nerve).", "distractors": ["Infraorbital nerve", "Supraorbital nerve", "Infratrochlear nerve"]}, {"context": "Left superior intercostal vein drains into ?", "truth": "Brachiocephalic vein", "distractors": ["Azygous vein", "Hemiazygous vein", "Internal thoracic vein"]}, {"context": "Early fusion of the coronal suture results in", "truth": "Brachycephaly", "distractors": ["Oxycephaly", "Trigonocephaly", "Scaphocephaly"]}, {"context": "Abnormal development of a joint is known as:", "truth": "Synostosis.", "distractors": ["Dysostosis.", "Both", "None"]}, {"context": "Which of the following is not present in posterior\ntriangle of neck?", "truth": "Hypoglossal nerve", "distractors": ["Phrenic nerve", "Subclavian nerve", "External jugular vein"]}, {"context": "Located medial to the third molar at the junction of the maxilla and the horizontal plate of the palatine bone:", "truth": "Greater palatine foramen", "distractors": ["Posterior nasal spine", "Mylohyoid line", "Pterygoid hamulus"]}, {"context": "In gene studies, the specific site to which the enzyme CRE recombinase binds is:", "truth": "LoxP site", "distractors": ["RE site", "NT site", "F site"]}, {"context": "Buccinator is pierced by all of the following except:", "truth": "Buccal branch of mandibular nerve", "distractors": ["Labial branch of facial nerve", "Parotid duct", "Molar mucous glands"]}, {"context": "Broca's area is related to", "truth": "Word formation", "distractors": ["Reading", "Sentence formation", "Comprehension"]}, {"context": "All of the following are carried by the dorsal column except?", "truth": "Pain", "distractors": ["Proprioception", "Vibration", "Touch"]}, {"context": "Umblical cord contains:", "truth": "2 arteries & 1 vein", "distractors": ["3 arteries & 1 vein", "1 artery& 3 veins", "1 artery & 1 vein"]}, {"context": "Branchial fistula is persistent of:", "truth": "2nd branchial cleft.", "distractors": ["1st branchial cleft.", "1st branchial arch.", "2nd branchial arch."]}, {"context": "Loss of flexion in the interphalangeal joint of thumb in supracondylar fracture is due to involvement of which nerve", "truth": "Anterior interosseous", "distractors": ["Posterior interosseous", "Median", "Ulnar"]}, {"context": "Motor division of trigeminal division comes out via:", "truth": "Foramen ovale", "distractors": ["Foramen spinosum", "Foramen magnum", "Foramen lacerum"]}, {"context": "House Brackman grading scale used for evaluation of which nerve?", "truth": "Facial nerve", "distractors": ["Hypoglossal", "Vagus", "Trigeminal"]}, {"context": "Incus and malleus are derived from:", "truth": "Dorsal end of meckels cartilage.", "distractors": ["Ventral end of meckels cartilage.", "Inferior end of meckels cartilage.", "Any of the above."]}, {"context": "Golgi apparatus in serous acinar cells is at:", "truth": "Supranuclear", "distractors": ["Apical", "Adjacent to nucleus", "Basal"]}, {"context": "Nociceptive signals are transmitted primarily to which of the following?", "truth": "Nucleus caudalis", "distractors": ["Limbic system", "Reticular system", "Superior cervical ganglion"]}, {"context": "The nerve which constitutes the sensory nerve supply of capsule of TMJ is:", "truth": "Auriculotemporal nerve", "distractors": ["Facial nerve", "Masseteric nerve", "Auricular nerve"]}, {"context": "Which of the following marked muscles is Involved in Opening of jaw?", "truth": "A", "distractors": ["B", "C", "D"]}, {"context": "Which part of body is underdeveloped at birth:", "truth": "Face.", "distractors": ["Eyes", "Ears.", "Brain"]}, {"context": "Preganglionic parasympathetic fibres to the Otic ganglion are carried in the:", "truth": "Lesser petrosal nerve", "distractors": ["Greater petrosal nerve", "Chorda tympani", "Auriculotemporal nerve"]}, {"context": "The secretion of salivary gland may be described as?", "truth": "Exocrine and merocrine", "distractors": ["Exocrine and holocrine", "Endocrine and holocrine", "Endocrine and merocrine"]}, {"context": "Tensor veli palatini is supplied by:", "truth": "Trigeminal nerve", "distractors": ["Facial nerve", "Glossopharyngeal nerve", "Pharyngeal plexus"]}, {"context": "All of the following muscles are derived from pharyngeal arches except:", "truth": "Levator palpebrae superioris", "distractors": ["Tensor tympani", "Palatine tensor", "Orbicularis oculi"]}, {"context": "Auriculotemporal nerve encircles which artery", "truth": "Middle meningeal artery", "distractors": ["Superficial temporal artery", "Superficial temporal vein", "Deep temporal"]}, {"context": "Ligamentum flavum consists of:", "truth": "Elastin", "distractors": ["Type-II collagen", "Type-III collagen", "Reticulin"]}, {"context": "Position of adenoid is in the ?", "truth": "Nasopharynx", "distractors": ["Hypopharynx", "Oropharynx", "Trachea"]}, {"context": "Anterior two third of the tongue is demarcated from the posterior one third by: plexus, 2-long thoracic plexus, 2-long thoracic", "truth": "Sulcus terminalis", "distractors": ["Passavant's ridge", "Circurnvallatepapillae", "Filifonn papilla"]}, {"context": "The primitives palate is formed from:", "truth": "Frontonasal process.", "distractors": ["2 palatal process.", "Maxillary process.", "All of the above."]}, {"context": "Which is not a branch of the external carotid aery supplying nasal septum?", "truth": "anterior ethmoidal", "distractors": ["Sphenopalatine", "greater palatine", "superior labial"]}, {"context": "Common carotid artery divides to ICA & ECA at:", "truth": "Thyroid cartilage", "distractors": ["Cricoid cartilage", "1st tracheal ring", "Cricothyroid membrane"]}, {"context": "Which of the following is unpaired bone of facial skeleton:", "truth": "Vomer", "distractors": ["Nasal", "Lacrimal", "Inferior nasal concha"]}, {"context": "Nerve supply of the mucosa of larynx, from epiglottis to the level of the cords is :", "truth": "Superior laryngeal", "distractors": ["External laryngeal", "External laryngeal and recurrent laryngeal", "Internal laryngeal and recurrent laryngeal"]}, {"context": "Which of the following muscle is not inseed to the greater tubercle of humerus?", "truth": "Subscapularis", "distractors": ["Supraspinatus", "lnfraspinatus", "Teres minor"]}, {"context": "Duct of parotid gland crosses over masseter muscle and pierces the:", "truth": "Buccinator muscle", "distractors": ["Superior constrictor", "Masseter", "Zygomaticus major"]}, {"context": "Lateral movement of condyle takes place by:", "truth": "Contralateral lateral pterygoid", "distractors": ["Ispilateral lateral pterygoid", "Same side medial pterygoid", "None of the above"]}]}