{
  "problem": "millennium_problems",
  "description": "Clay Millennium Prize Problems - statements, partial results, and known approaches.",
  "facts": [
    {
      "id": "mp01_riemann_statement",
      "context": "The Riemann Hypothesis concerns the zeros of the Riemann zeta function ζ(s). It states that:",
      "truth": "all non-trivial zeros have real part equal to 1/2 (lie on the critical line)",
      "distractors": [
        "all zeros are real numbers",
        "there are finitely many zeros",
        "zeros can have any real part between 0 and 1"
      ],
      "cluster": "riemann"
    },
    {
      "id": "mp02_riemann_verified",
      "context": "Computational verification of the Riemann Hypothesis has confirmed:",
      "truth": "the first 10+ trillion zeros all lie on the critical line",
      "distractors": [
        "a counterexample exists near 10^100",
        "only the first 1000 zeros have been checked",
        "computation cannot verify any zeros"
      ],
      "cluster": "riemann"
    },
    {
      "id": "mp03_riemann_consequence",
      "context": "If the Riemann Hypothesis is true, it would imply:",
      "truth": "the prime counting function π(x) has error term O(√x log x)",
      "distractors": [
        "there are finitely many primes",
        "no improvement to prime number theorem",
        "all primes are of form 6k±1"
      ],
      "cluster": "riemann"
    },
    {
      "id": "mp04_pnp_statement",
      "context": "The P versus NP problem asks whether:",
      "truth": "every problem whose solution can be verified in polynomial time can also be solved in polynomial time",
      "distractors": [
        "all problems can be solved efficiently",
        "no problems can be solved efficiently",
        "verification is always harder than solving"
      ],
      "cluster": "pnp"
    },
    {
      "id": "mp05_pnp_barriers",
      "context": "The relativization barrier (Baker-Gill-Solovay) shows that:",
      "truth": "any proof of P≠NP cannot relativize (cannot work for all oracles)",
      "distractors": [
        "P=NP is provable using diagonalization",
        "the problem is undecidable",
        "there are no barriers to solving P vs NP"
      ],
      "cluster": "pnp"
    },
    {
      "id": "mp06_pnp_natural",
      "context": "The natural proofs barrier (Razborov-Rudich) shows that:",
      "truth": "if one-way functions exist, certain proof techniques cannot separate P from NP",
      "distractors": [
        "natural proofs can solve P vs NP",
        "cryptography is unrelated to P vs NP",
        "all circuit lower bounds are natural proofs"
      ],
      "cluster": "pnp"
    },
    {
      "id": "mp07_ns_statement",
      "context": "The Navier-Stokes existence and smoothness problem asks whether:",
      "truth": "smooth solutions exist globally in time for 3D, or if singularities can form",
      "distractors": [
        "solutions always exist in 2D (already proven)",
        "the equations have no solutions",
        "only steady-state solutions matter"
      ],
      "cluster": "navier_stokes"
    },
    {
      "id": "mp08_ns_2d",
      "context": "For 2D Navier-Stokes, global existence and regularity:",
      "truth": "is proven - smooth solutions exist for all time (Ladyzhenskaya 1969)",
      "distractors": [
        "remains unsolved like 3D",
        "blowup is known to occur",
        "only weak solutions exist"
      ],
      "cluster": "navier_stokes"
    },
    {
      "id": "mp09_hodge_statement",
      "context": "The Hodge Conjecture states that for projective algebraic varieties:",
      "truth": "certain cohomology classes (Hodge classes) are rational linear combinations of algebraic cycles",
      "distractors": [
        "all cohomology classes are algebraic",
        "no cohomology classes are algebraic",
        "only applies to curves"
      ],
      "cluster": "hodge"
    },
    {
      "id": "mp10_bsd_statement",
      "context": "The Birch and Swinnerton-Dyer Conjecture relates:",
      "truth": "the rank of an elliptic curve to the order of vanishing of its L-function at s=1",
      "distractors": [
        "elliptic curves to prime numbers directly",
        "only applies to curves over finite fields",
        "the conjecture has been proven for all curves"
      ],
      "cluster": "bsd"
    },
    {
      "id": "mp11_bsd_partial",
      "context": "The BSD conjecture has been proven for elliptic curves:",
      "truth": "of analytic rank 0 or 1 (Gross-Zagier, Kolyvagin)",
      "distractors": [
        "of all ranks",
        "of no ranks",
        "only over finite fields"
      ],
      "cluster": "bsd"
    },
    {
      "id": "mp12_yangmills_statement",
      "context": "The Yang-Mills existence and mass gap problem asks to prove:",
      "truth": "quantum Yang-Mills theory exists in 4D and has a positive mass gap",
      "distractors": [
        "Yang-Mills has no mass gap",
        "the theory only exists in 2D",
        "classical solutions suffice"
      ],
      "cluster": "yangmills"
    }
  ]
}
